sm/sm.v
module sm(a, b, state, clk, rst);
	input a, b;
	output [1:0] state;
	input clk, rst;
	reg [1:0] state, nstate;
	always @(posedge clk or posedge rst) begin
		if(rst) state <= 0;
		else state <= nstate;
	end
	always @(*) begin
		if(({a,b} == 2'b00) || ({a,b} == 2'b00)) nstate = state;
		else begin
			case (state)
			// synopsys full_case parallel_case
			2'b00: if(a) nstate = 2'b01;
			2'b01: begin
				if(a) nstate = 2'b11;
				if(b) nstate = 2'b00;
			end
			2'b11: if(b) nstate = 2'b01;
			endcase
		end
	end
endmodule
module test;
	reg a, b, clk, rst;
	wire [1:0] state;
	sm sm(a, b, state, clk, rst);
	always #5 clk = ~clk;
initial begin
$dumpfile("sm.vcd");
$dumpvars(0, test);
rst = 1'b1;
clk = 1'b0;
a = 1'b0;
b = 1'b0;
#20
rst = 1'b0;
#20
a = 1'b1;
#10
a = 1'b0;
#10
a = 1'b1;
#20
a = 1'b0;
b = 1'b1;
#30
$finish;
end
endmodule

sm/sm.vcd
$date
	Fri May 18 09:59:56 2018
$end
$version
	Icarus Verilog
$end
$timescale
	1s
$end
$scope module test $end
$var wire 2 ! state [1:0] $end
$var reg 1 " a $end
$var reg 1 # b $end
$var reg 1 $ clk $end
$var reg 1 % rst $end
$scope module sm $end
$var wire 1 " a $end
$var wire 1 # b $end
$var wire 1 $ clk $end
$var wire 1 % rst $end
$var reg 2 & nstate [1:0] $end
$var reg 2 ' state [1:0] $end
$upscope $end
$upscope $end
$enddefinitions $end
#0
$dumpvars
b0 '
b0 &
1%
0$
0#
0"
b0 !
$end
#5
1$
#10
0$
#15
1$
#20
0$
0%
#25
1$
#30
0$
#35
1$
#40
b1 &
0$
1"
#45
b11 &
b1 !
b1 '
1$
#50
b1 &
0$
0"
#55
1$
#60
b11 &
0$
1"
#65
b11 !
b11 '
1$
#70
0$
#75
1$
#80
b1 &
0$
1#
0"
#85
b0 &
b1 !
b1 '
1$
#90
0$
#95
b0 !
b0 '
1$
