genrand/genrand.v
module genrand(clk,rst,seed,randnum);
   input clk,rst;
   input [15:0] seed;
   output [15:0] randnum;
   reg [15:0] xx;
   reg [15:0] randnum;

   always @(posedge clk)begin
      if(rst)begin//はじめだけseed値を代入する
	 randnum=seed;
      end
      xx=randnum;
      xx=xx^xx<<3;
      xx=xx^xx>>11;
      xx=xx^xx<<7;
      randnum=xx;
   end
endmodule // genrand

module test;
   reg clk,rst;
   reg [15:0] seed;
   wire [15:0] randnum;
   genrand genrand(clk,rst,seed,randnum);
   always #5 clk=~clk;
   initial begin
      $dumpfile("genrand.vcd");
      $dumpvars(0,test);
      rst=1;
      clk=0;
      seed=4;
      #20;
      rst=0;
      #500;
      $finish;
   end // initial begin
endmodule // test

genrand/genrand.vcd
$date
	Wed Jul  4 20:22:32 2018
$end
$version
	Icarus Verilog
$end
$timescale
	1s
$end
$scope module test $end
$var wire 16 ! randnum [15:0] $end
$var reg 1 " clk $end
$var reg 1 # rst $end
$var reg 16 $ seed [15:0] $end
$scope module genrand $end
$var wire 1 " clk $end
$var wire 1 # rst $end
$var wire 16 % seed [15:0] $end
$var reg 16 & randnum [15:0] $end
$var reg 16 ' xx [15:0] $end
$upscope $end
$upscope $end
$enddefinitions $end
#0
$dumpvars
bx '
bx &
b100 %
b100 $
1#
0"
bx !
$end
#5
b1001000100100 '
b1001000100100 !
b1001000100100 &
1"
#10
0"
#15
b1001000100100 '
b1001000100100 !
b1001000100100 &
1"
#20
0"
0#
#25
b100100010100 !
b100100010100 &
b100100010100 '
1"
#30
0"
#35
b1001111110111100 !
b1001111110111100 &
b1001111110111100 '
1"
#40
0"
#45
b100101001010000 !
b100101001010000 &
b100101001010000 '
1"
#50
0"
#55
b111000101010011 !
b111000101010011 &
b111000101010011 '
1"
#60
0"
#65
b1000111010100 !
b1000111010100 &
b1000111010100 '
1"
#70
0"
#75
b10110011100111 !
b10110011100111 &
b10110011100111 '
1"
#80
0"
#85
b1010000011010110 !
b1010000011010110 &
b1010000011010110 '
1"
#90
0"
#95
b1001111101110010 !
b1001111101110010 &
b1001111101110010 '
1"
#100
0"
#105
b1001111101110 !
b1001111101110 &
b1001111101110 '
1"
#110
0"
#115
b1100101100001111 !
b1100101100001111 &
b1100101100001111 '
1"
#120
0"
#125
b10000111100101 !
b10000111100101 &
b10000111100101 '
1"
#130
0"
#135
b100101011001000 !
b100101011001000 &
b100101011001000 '
1"
#140
0"
#145
b101100100001011 !
b101100100001011 &
b101100100001011 '
1"
#150
0"
#155
b11000111000001 !
b11000111000001 &
b11000111000001 '
1"
#160
0"
#165
b101000011011110 !
b101000011011110 &
b101000011011110 '
1"
#170
0"
#175
b1100110000110100 !
b1100110000110100 &
b1100110000110100 '
1"
#180
0"
#185
b110110100000001 !
b110110100000001 &
b110110100000001 '
1"
#190
0"
#195
b1000000110001001 !
b1000000110001001 &
b1000000110001001 '
1"
#200
0"
#205
b110010111010000 !
b110010111010000 &
b110010111010000 '
1"
#210
0"
#215
b1110011111011001 !
b1110011111011001 &
b1110011111011001 '
1"
#220
0"
#225
b101110000001010 !
b101110000001010 &
b101110000001010 '
1"
#230
0"
#235
b1001101011001101 !
b1001101011001101 &
b1001101011001101 '
1"
#240
0"
#245
b1101010101100 !
b1101010101100 &
b1101010101100 '
1"
#250
0"
#255
b10010101010101 !
b10010101010101 &
b10010101010101 '
1"
#260
0"
#265
b1111000111111100 !
b1111000111111100 &
b1111000111111100 '
1"
#270
0"
#275
b111011110010011 !
b111011110010011 &
b111011110010011 '
1"
#280
0"
#285
b100001000010010 !
b100001000010010 &
b100001000010010 '
1"
#290
0"
#295
b1011010001000 !
b1011010001000 &
b1011010001000 '
1"
#300
0"
#305
b1100110011011100 !
b1100110011011100 &
b1100110011011100 '
1"
#310
0"
#315
b1011111010101001 !
b1011111010101001 &
b1011111010101001 '
1"
#320
0"
#325
b1011111111101000 !
b1011111111101000 &
b1011111111101000 '
1"
#330
0"
#335
b1000010100000 !
b1000010100000 &
b1000010100000 '
1"
#340
0"
#345
b100110010110010 !
b100110010110010 &
b100110010110010 '
1"
#350
0"
#355
b1011101010100111 !
b1011101010100111 &
b1011101010100111 '
1"
#360
0"
#365
b1010011010010010 !
b1010011010010010 &
b1010011010010010 '
1"
#370
0"
#375
b1001101000010000 !
b1001101000010000 &
b1001101000010000 '
1"
#380
0"
#385
b11000011001 !
b11000011001 &
b11000011001 '
1"
#390
0"
#395
b101110101010111 !
b101110101010111 &
b101110101010111 '
1"
#400
0"
#405
b100101101111001 !
b100101101111001 &
b100101101111001 '
1"
#410
0"
#415
b100100100110011 !
b100100100110011 &
b100100100110011 '
1"
#420
0"
#425
b101010100101011 !
b101010100101011 &
b101010100101011 '
1"
#430
0"
#435
b1100101001101100 !
b1100101001101100 &
b1100101001101100 '
1"
#440
0"
#445
b1011010011111 !
b1011010011111 &
b1011010011111 '
1"
#450
0"
#455
b1001101111110011 !
b1001101111110011 &
b1001101111110011 '
1"
#460
0"
#465
b111010111100011 !
b111010111100011 &
b111010111100011 '
1"
#470
0"
#475
b1010101011100000 !
b1010101011100000 &
b1010101011100000 '
1"
#480
0"
#485
b1001111111 !
b1001111111 &
b1001111111 '
1"
#490
0"
#495
b1101001100000101 !
b1101001100000101 &
b1101001100000101 '
1"
#500
0"
#505
b1101100100100100 !
b1101100100100100 &
b1101100100100100 '
1"
#510
0"
#515
b1001100000110 !
b1001100000110 &
b1001100000110 '
1"
